lfem/__init__.py
lfem/mesh.cpython-311-x86_64-linux-gnu.so
lfem/py.typed
lfem-0.1.0.dist-info/licenses/LICENSE
lfem-0.1.0.dist-info/METADATA
lfem-0.1.0.dist-info/WHEEL
lfem-0.1.0.dist-info/top_level.txt
lfem-0.1.0.dist-info/RECORD
