Metadata-Version: 2.4
Name: lfem
Version: 0.1.0
Summary: Add your description here
Author: Lepy
Author-email: Lepy <lep@lepy.de>
Requires-Python: >=3.11,<3.12
License-File: LICENSE
Requires-Dist: numpy>=2.4.1
Requires-Dist: pandas>=2.3.3
Dynamic: author
Dynamic: license-file
Dynamic: requires-python
